hw/4/rv64_alu.v
`define ALU_ADD 0
`define ALU_ADDW 1
`define ALU_SUB 2
`define ALU_SUBW 3
`define ALU_SLL 4
`define ALU_SLLW 5
`define ALU_SRA 6
`define ALU_SRAW 7
module rv64_alu(
	input [63:0] a,
	input [63:0] b,
	input [2:0] op, // op can be any of values`define'd above
	output [63:0] c
);

	reg [63:0] out;
	assign c = out;
	always @(*) begin
		case (op)
			3'd0: out = $signed(a) + $signed(b);
			3'd1: out = $signed(a[31:0]) + $signed(b[31:0]);
			3'd2: out = $signed(a) - $signed(b);
			3'd3: out = $signed(a[31:0]) - $signed(b[31:0]);
			3'd4: out = $unsigned(a) << b;
			3'd5: out = $signed($unsigned(a[31:0]) << b);
			3'd6: out = $signed(a) >> b;
			3'd7: out = $signed(a) >> b;
			default: out = 64'b0;
		endcase
	end

endmodule

hw/4/rv64_alu_testbench.v
module rv64_alu_testbench();
	reg [63:0] a;
	reg [63:0] b;
	reg [2:0] op;
	wire [63:0] c;
	initial a = 64'b0;
	initial b = 64'b0;
	initial op = 3'b0;

	rv64_alu dut(
		.a(a),
		.b(b),
		.op(op),
		.c(c)
	);

	initial begin
		$dumpfile("rv64_alu_testbench.vcd");
		$dumpvars(0, rv64_alu_testbench);

		#100;
		a = 64'h210000000;
		b = 64'h100000000;
		op = 3'd0;
		#100;
		op = 3'd1;
		#100;
		op = 3'd2;
		#100;
		op = 3'd3;
		#100;
		op = 3'd4;
		#100;
		op = 3'd5;
		#100;
		op = 3'd6;
		#100;
		op = 3'd7;
		#100;
		op = 3'd0;
		$finish();
	end

endmodule

hw/4/rv64_alu_testbench.vcd
$date
	Fri Oct  4 17:02:32 2019
$end
$version
	Icarus Verilog
$end
$timescale
	1s
$end
$scope module rv64_alu_testbench $end
$var wire 64 ! c [63:0] $end
$var reg 64 " a [63:0] $end
$var reg 64 # b [63:0] $end
$var reg 3 $ op [2:0] $end
$scope module dut $end
$var wire 64 % a [63:0] $end
$var wire 64 & b [63:0] $end
$var wire 64 ' c [63:0] $end
$var wire 3 ( op [2:0] $end
$var reg 64 ) out [63:0] $end
$upscope $end
$upscope $end
$enddefinitions $end
#0
$dumpvars
b0 )
b0 (
b0 '
b0 &
b0 %
b0 $
b0 #
b0 "
b0 !
$end
#100
b1100010000000000000000000000000000 !
b1100010000000000000000000000000000 '
b1100010000000000000000000000000000 )
b100000000000000000000000000000000 #
b100000000000000000000000000000000 &
b1000010000000000000000000000000000 "
b1000010000000000000000000000000000 %
#200
b10000000000000000000000000000 !
b10000000000000000000000000000 '
b10000000000000000000000000000 )
b1 $
b1 (
#300
b100010000000000000000000000000000 !
b100010000000000000000000000000000 '
b100010000000000000000000000000000 )
b10 $
b10 (
#400
b10000000000000000000000000000 !
b10000000000000000000000000000 '
b10000000000000000000000000000 )
b11 $
b11 (
#500
b1000010000000000000000000000000000 !
b1000010000000000000000000000000000 '
b1000010000000000000000000000000000 )
b100 $
b100 (
#600
b10000000000000000000000000000 !
b10000000000000000000000000000 '
b10000000000000000000000000000 )
b101 $
b101 (
#700
b1000010000000000000000000000000000 !
b1000010000000000000000000000000000 '
b1000010000000000000000000000000000 )
b110 $
b110 (
#800
b111 $
b111 (
#900
b1100010000000000000000000000000000 !
b1100010000000000000000000000000000 '
b1100010000000000000000000000000000 )
b0 $
b0 (
