hw/2/alu.v
module alu (input [31:0] a, input [31:0] b, input [2:0] sel, output [31:0] out_data);
	reg [31:0] out;
	assign out_data = out;
	reg [32:0] carry;
	always @(*) begin
		case (sel)
			3'b000: out <= $signed(a) + $signed(b);
			3'b001: {carry, out} <= $unsigned(a) + $unsigned(b);
			3'b010:	out <= $signed(a) - $signed(b);
			3'b011:	out <= a - b;
			3'b100: out <= a & b;
			3'b101: out <= a | b;
			3'b110: out <= a >>> b;
			3'b111: out <= a >> b;
			default: out <= a + b;
		endcase
	end
endmodule

hw/2/alu_testbench.v
`timescale 1ns / 1ns

module alu_testbench();
	reg [31:0] a;
	reg [31:0] b;
	reg [2:0] sel;
	
	wire[31:0] out_data;
	reg fi = 1'b0;

	alu tu(
		.a(a),
		.b(b),
		.sel(sel),
		.out_data(out_data)
	);

	initial begin
		$dumpfile("alu_testbench.vcd");
		$dumpvars(0, alu_testbench);

		a = 32'd10;
		b = 32'd2;
		b = -b;
		sel = 3'b0;
		#1;
		$display("Signed Add: a = %0d, b = %0d, out = %0d", a, $signed(b), out_data);
		if (out_data != 32'd8) begin
			fi = 1'b1;
		end
		sel = 3'b1;
		a = 32'd1;
		#1;
		$display("Unsiged Add: a = %0d, b = %0d, out = %0d", a, $unsigned(b), out_data);
		if (out_data != 32'd4294967295) begin
			fi = 1'b1;
		end
		sel = 3'b10;
		a = 32'd10;
		b = 32'd2;
		b = -b;
		#1;
		$display("Signed Subtract: a = %0d, b = %0d, out = %0d", a, $signed(b), out_data);
		if (out_data != 32'd12) begin
			fi = 1'b1;
		end
		sel = 3'b11;
		a = b;
		b = 32'd1;
		#1;
		$display("Unsigned Subtract: a = %0d, b = %0d, out = %0d", a, $unsigned(b), out_data);
		if (out_data != 32'd4294967293) begin
			fi = 1'b1;
		end
		sel = 3'b100;
		a = 32'd0;
		b = 32'd1;
		#1;
		$display("And: a = %0d, b = %0d, out = %0d", a, b, out_data);
		if (out_data != 32'd0) begin
			fi = 1'b1;
		end
		sel = 3'b101;
		#1;
		$display("Or: a = %0d, b = %0d, out = %0d", a, b, out_data);
		if (out_data != 32'd1) begin
			fi = 1'b1;
		end
		sel = 3'b110;
		a = 32'd4;
		a = -a;
		b = 32'd1;
		#1;
		$display("Shift Right Arithmetic: a = %0d, b = %0d, out = %0d", $signed(a), b, out_data);
		if (out_data != 32'd2147483646) begin
			fi = 1'b1;
		end
		sel = 3'b111;
		a = 32'd4;
		b = 32'd1;
		#1;
		$display("Shift Right Logical: a = %0d, b = %0d, out = %0d", $signed(a), b, out_data);
		if (out_data != 32'd2) begin
			fi = 1'b1;
		end
		
		if (fi == 1'b0) begin
			$display("Pass");
		end else begin
			$display("Fail");
		end
		$finish();
	end
endmodule

hw/2/alu_testbench.vcd
$date
	Fri Sep 20 15:55:12 2019
$end
$version
	Icarus Verilog
$end
$timescale
	1ns
$end
$scope module alu_testbench $end
$var wire 32 ! out_data [31:0] $end
$var reg 32 " a [31:0] $end
$var reg 32 # b [31:0] $end
$var reg 1 $ fi $end
$var reg 3 % sel [2:0] $end
$scope module tu $end
$var wire 32 & a [31:0] $end
$var wire 32 ' b [31:0] $end
$var wire 32 ( out_data [31:0] $end
$var wire 3 ) sel [2:0] $end
$var reg 33 * carry [32:0] $end
$var reg 32 + out [31:0] $end
$upscope $end
$upscope $end
$enddefinitions $end
#0
$dumpvars
b1000 +
bx *
b0 )
b1000 (
b11111111111111111111111111111110 '
b1010 &
b0 %
0$
b11111111111111111111111111111110 #
b1010 "
b1000 !
$end
#1
b0 *
b11111111111111111111111111111111 !
b11111111111111111111111111111111 (
b11111111111111111111111111111111 +
b1 "
b1 &
b1 %
b1 )
#2
b1100 !
b1100 (
b1100 +
b11111111111111111111111111111110 #
b11111111111111111111111111111110 '
b1010 "
b1010 &
b10 %
b10 )
#3
b11111111111111111111111111111101 !
b11111111111111111111111111111101 (
b11111111111111111111111111111101 +
b1 #
b1 '
b11111111111111111111111111111110 "
b11111111111111111111111111111110 &
b11 %
b11 )
#4
b0 !
b0 (
b0 +
b0 "
b0 &
b100 %
b100 )
#5
b1 !
b1 (
b1 +
b101 %
b101 )
#6
b1111111111111111111111111111110 !
b1111111111111111111111111111110 (
b1111111111111111111111111111110 +
b11111111111111111111111111111100 "
b11111111111111111111111111111100 &
b110 %
b110 )
#7
b10 !
b10 (
b10 +
b100 "
b100 &
b111 %
b111 )
