hw/3/pattern.v
module pattern (input clk, input rst, input sig, output out);

localparam	S0 = 3'd0;
localparam	S1 = 3'd1;
localparam	S2 = 3'd2;
localparam	S4 = 3'd3;
localparam	S9 = 3'd4;
localparam	S18 = 3'd5;

reg [2:0] CurrentState;
reg [2:0] NextState;

assign out = (CurrentState == S18);

always @(posedge clk) begin
	if (rst) begin
		CurrentState <= S0;
	end else begin
		CurrentState <= NextState;
	end
end

always @(*) begin
	NextState = CurrentState;
	case (CurrentState)
		S0: begin
			if (sig == 1'b1) NextState = S1;
		end
		S1: begin
			if (sig == 1'b0) NextState = S2;
		end
		S2: begin
			if (sig == 1'b0) NextState = S4;
			else NextState = S1;
		end
		S4: begin
			if (sig == 1'b1) NextState = S9;
			else NextState = S0;
		end
		S9: begin
			if (sig == 1'b0) NextState = S18;
			else NextState = S1;
		end
		S18: begin
			if (sig == 1'b1) NextState = S1;
			else NextState = S0;
		end
	endcase
end
endmodule

hw/3/pattern_testbench.v
`timescale 1ns/1ns

module pattern_testbench();
	reg clk;
	reg reset;
	reg sig;
	wire out;
	reg fi = 1'b0;
	initial clk = 0;
	initial reset = 1'b0;
	initial sig = 1'b0;

	always #(10) clk <= ~clk;

	pattern dut(
		.clk(clk),
		.rst(reset),
		.sig(sig),
		.out(out)
	);

	initial begin
		$dumpfile("pattern_testbench.vcd");
		$dumpvars(0, pattern_testbench);
		
		@(posedge clk); #1;
		reset = 1;
		@(posedge clk); #1;
		reset = 0;
		sig = 1;
		@(posedge clk); #1;
		sig = 0;
		repeat (2) @(posedge clk); #1;
		sig = 1;
		@(posedge clk); #1;
		sig = 0;
		@(posedge clk); #1;
		if (out == 1'b0) fi = 1'b1;
		repeat (50) @(posedge clk); #1;
		if (out == 1'b1) fi = 1'b1;
		@(posedge clk); #1;
		sig = 1;
		@(posedge clk); #1;
		sig = 0;
		@(posedge clk); #1;
		sig = 1;
		@(posedge clk); #1;
		sig = 0;
		@(posedge clk); #1;
		@(posedge clk); #1;
		sig = 1;
		@(posedge clk); #1;
		@(posedge clk); #1;
		sig = 0;
		@(posedge clk); #1;
		@(posedge clk); #1;
		sig = 1;
		@(posedge clk); #1;
		sig = 0;
		@(posedge clk); #1;
		if (out == 1'b0) fi = 1'b1;
		$display("Out: %0d", out);
		if (fi) $display("Fail");
		else $display("Pass");
		$finish();
	end
endmodule

hw/3/pattern_testbench.vcd
$date
	Mon Sep 23 23:44:49 2019
$end
$version
	Icarus Verilog
$end
$timescale
	1ns
$end
$scope module pattern_testbench $end
$var wire 1 ! out $end
$var reg 1 " clk $end
$var reg 1 # fi $end
$var reg 1 $ reset $end
$var reg 1 % sig $end
$scope module dut $end
$var wire 1 " clk $end
$var wire 1 $ rst $end
$var wire 1 % sig $end
$var wire 1 ! out $end
$var reg 3 & CurrentState [2:0] $end
$var reg 3 ' NextState [2:0] $end
$upscope $end
$upscope $end
$enddefinitions $end
#0
$dumpvars
bx '
bx &
0%
0$
0#
0"
x!
$end
#10
1"
#11
1$
#20
0"
#30
b0 '
0!
b0 &
1"
#31
b1 '
1%
0$
#40
0"
#50
b1 &
1"
#51
b10 '
0%
#60
0"
#70
b11 '
b10 &
1"
#80
0"
#90
b0 '
b11 &
1"
#91
b100 '
1%
#100
0"
#110
b1 '
b100 &
1"
#111
b101 '
0%
#120
0"
#130
b0 '
1!
b101 &
1"
#140
0"
#150
0!
b0 &
1"
